Classfile /home/florian/Documents/fh/WS23_24/Compilerbau/vm/main/tests/data/inheritance/shadowed_field/Main.class
  Last modified 10.01.2024; size 441 bytes
  MD5 checksum be939a5c4e4b14f045e4948ff9f539c6
  Compiled from "Main.java"
public class Main
  minor version: 0
  major version: 52
  flags: ACC_PUBLIC, ACC_SUPER
Constant pool:
   #1 = Methodref          #6.#22         // java/lang/Object."<init>":()V
   #2 = Class              #23            // B
   #3 = Methodref          #2.#24         // B."<init>":(I)V
   #4 = Methodref          #2.#25         // B.printIt:()V
   #5 = Class              #26            // Main
   #6 = Class              #27            // java/lang/Object
   #7 = Utf8               <init>
   #8 = Utf8               ()V
   #9 = Utf8               Code
  #10 = Utf8               LineNumberTable
  #11 = Utf8               LocalVariableTable
  #12 = Utf8               this
  #13 = Utf8               LMain;
  #14 = Utf8               main
  #15 = Utf8               ([Ljava/lang/String;)V
  #16 = Utf8               args
  #17 = Utf8               [Ljava/lang/String;
  #18 = Utf8               b
  #19 = Utf8               LB;
  #20 = Utf8               SourceFile
  #21 = Utf8               Main.java
  #22 = NameAndType        #7:#8          // "<init>":()V
  #23 = Utf8               B
  #24 = NameAndType        #7:#28         // "<init>":(I)V
  #25 = NameAndType        #29:#8         // printIt:()V
  #26 = Utf8               Main
  #27 = Utf8               java/lang/Object
  #28 = Utf8               (I)V
  #29 = Utf8               printIt
{
  public Main();
    descriptor: ()V
    flags: ACC_PUBLIC
    Code:
      stack=1, locals=1, args_size=1
         0: aload_0
         1: invokespecial #1                  // Method java/lang/Object."<init>":()V
         4: return
      LineNumberTable:
        line 1: 0
      LocalVariableTable:
        Start  Length  Slot  Name   Signature
            0       5     0  this   LMain;

  public static void main(java.lang.String[]);
    descriptor: ([Ljava/lang/String;)V
    flags: ACC_PUBLIC, ACC_STATIC
    Code:
      stack=3, locals=2, args_size=1
         0: new           #2                  // class B
         3: dup
         4: bipush        10
         6: invokespecial #3                  // Method B."<init>":(I)V
         9: astore_1
        10: aload_1
        11: invokevirtual #4                  // Method B.printIt:()V
        14: return
      LineNumberTable:
        line 3: 0
        line 4: 10
        line 5: 14
      LocalVariableTable:
        Start  Length  Slot  Name   Signature
            0      15     0  args   [Ljava/lang/String;
           10       5     1     b   LB;
}
SourceFile: "Main.java"
