Classfile /home/florian/Documents/fh/WS23_24/Compilerbau/vm/main/tests/data/exceptions/subtype/Main.class
  Last modified 11.01.2024; size 919 bytes
  MD5 checksum ed97ab60172ce2ffe2a3096018a73966
  Compiled from "Main.java"
public class Main
  minor version: 0
  major version: 52
  flags: ACC_PUBLIC, ACC_SUPER
Constant pool:
   #1 = Methodref          #16.#37        // java/lang/Object."<init>":()V
   #2 = Class              #38            // A
   #3 = String             #39            // Oops
   #4 = Methodref          #2.#40         // A."<init>":(Ljava/lang/String;)V
   #5 = Class              #41            // java/lang/Throwable
   #6 = Fieldref           #42.#43        // java/lang/System.out:Ljava/io/PrintStream;
   #7 = String             #44            // caught e:
   #8 = Methodref          #45.#46        // java/io/PrintStream.println:(Ljava/lang/String;)V
   #9 = Methodref          #5.#47         // java/lang/Throwable.getMessage:()Ljava/lang/String;
  #10 = String             #48            // Huh?
  #11 = Methodref          #5.#40         // java/lang/Throwable."<init>":(Ljava/lang/String;)V
  #12 = String             #49            // caught a:
  #13 = Methodref          #2.#47         // A.getMessage:()Ljava/lang/String;
  #14 = String             #50            // did not catch e:
  #15 = Class              #51            // Main
  #16 = Class              #52            // java/lang/Object
  #17 = Utf8               <init>
  #18 = Utf8               ()V
  #19 = Utf8               Code
  #20 = Utf8               LineNumberTable
  #21 = Utf8               LocalVariableTable
  #22 = Utf8               this
  #23 = Utf8               LMain;
  #24 = Utf8               main
  #25 = Utf8               ([Ljava/lang/String;)V
  #26 = Utf8               e
  #27 = Utf8               Ljava/lang/Throwable;
  #28 = Utf8               a
  #29 = Utf8               LA;
  #30 = Utf8               args
  #31 = Utf8               [Ljava/lang/String;
  #32 = Utf8               StackMapTable
  #33 = Class              #41            // java/lang/Throwable
  #34 = Class              #38            // A
  #35 = Utf8               SourceFile
  #36 = Utf8               Main.java
  #37 = NameAndType        #17:#18        // "<init>":()V
  #38 = Utf8               A
  #39 = Utf8               Oops
  #40 = NameAndType        #17:#53        // "<init>":(Ljava/lang/String;)V
  #41 = Utf8               java/lang/Throwable
  #42 = Class              #54            // java/lang/System
  #43 = NameAndType        #55:#56        // out:Ljava/io/PrintStream;
  #44 = Utf8               caught e:
  #45 = Class              #57            // java/io/PrintStream
  #46 = NameAndType        #58:#53        // println:(Ljava/lang/String;)V
  #47 = NameAndType        #59:#60        // getMessage:()Ljava/lang/String;
  #48 = Utf8               Huh?
  #49 = Utf8               caught a:
  #50 = Utf8               did not catch e:
  #51 = Utf8               Main
  #52 = Utf8               java/lang/Object
  #53 = Utf8               (Ljava/lang/String;)V
  #54 = Utf8               java/lang/System
  #55 = Utf8               out
  #56 = Utf8               Ljava/io/PrintStream;
  #57 = Utf8               java/io/PrintStream
  #58 = Utf8               println
  #59 = Utf8               getMessage
  #60 = Utf8               ()Ljava/lang/String;
{
  public Main();
    descriptor: ()V
    flags: ACC_PUBLIC
    Code:
      stack=1, locals=1, args_size=1
         0: aload_0
         1: invokespecial #1                  // Method java/lang/Object."<init>":()V
         4: return
      LineNumberTable:
        line 1: 0
      LocalVariableTable:
        Start  Length  Slot  Name   Signature
            0       5     0  this   LMain;

  public static void main(java.lang.String[]);
    descriptor: ([Ljava/lang/String;)V
    flags: ACC_PUBLIC, ACC_STATIC
    Code:
      stack=3, locals=2, args_size=1
         0: new           #2                  // class A
         3: dup
         4: ldc           #3                  // String Oops
         6: invokespecial #4                  // Method A."<init>":(Ljava/lang/String;)V
         9: athrow
        10: astore_1
        11: getstatic     #6                  // Field java/lang/System.out:Ljava/io/PrintStream;
        14: ldc           #7                  // String caught e:
        16: invokevirtual #8                  // Method java/io/PrintStream.println:(Ljava/lang/String;)V
        19: getstatic     #6                  // Field java/lang/System.out:Ljava/io/PrintStream;
        22: aload_1
        23: invokevirtual #9                  // Method java/lang/Throwable.getMessage:()Ljava/lang/String;
        26: invokevirtual #8                  // Method java/io/PrintStream.println:(Ljava/lang/String;)V
        29: new           #5                  // class java/lang/Throwable
        32: dup
        33: ldc           #10                 // String Huh?
        35: invokespecial #11                 // Method java/lang/Throwable."<init>":(Ljava/lang/String;)V
        38: athrow
        39: astore_1
        40: getstatic     #6                  // Field java/lang/System.out:Ljava/io/PrintStream;
        43: ldc           #12                 // String caught a:
        45: invokevirtual #8                  // Method java/io/PrintStream.println:(Ljava/lang/String;)V
        48: getstatic     #6                  // Field java/lang/System.out:Ljava/io/PrintStream;
        51: aload_1
        52: invokevirtual #13                 // Method A.getMessage:()Ljava/lang/String;
        55: invokevirtual #8                  // Method java/io/PrintStream.println:(Ljava/lang/String;)V
        58: goto          80
        61: astore_1
        62: getstatic     #6                  // Field java/lang/System.out:Ljava/io/PrintStream;
        65: ldc           #14                 // String did not catch e:
        67: invokevirtual #8                  // Method java/io/PrintStream.println:(Ljava/lang/String;)V
        70: getstatic     #6                  // Field java/lang/System.out:Ljava/io/PrintStream;
        73: aload_1
        74: invokevirtual #9                  // Method java/lang/Throwable.getMessage:()Ljava/lang/String;
        77: invokevirtual #8                  // Method java/io/PrintStream.println:(Ljava/lang/String;)V
        80: return
      Exception table:
         from    to  target type
             0    10    10   Class java/lang/Throwable
            29    39    39   Class A
            29    58    61   Class java/lang/Throwable
      LineNumberTable:
        line 4: 0
        line 5: 10
        line 6: 11
        line 7: 19
        line 11: 29
        line 12: 39
        line 13: 40
        line 14: 48
        line 19: 58
        line 16: 61
        line 17: 62
        line 18: 70
        line 20: 80
      LocalVariableTable:
        Start  Length  Slot  Name   Signature
           11      18     1     e   Ljava/lang/Throwable;
           40      18     1     a   LA;
           62      18     1     e   Ljava/lang/Throwable;
            0      81     0  args   [Ljava/lang/String;
      StackMapTable: number_of_entries = 4
        frame_type = 74 /* same_locals_1_stack_item */
          stack = [ class java/lang/Throwable ]
        frame_type = 92 /* same_locals_1_stack_item */
          stack = [ class A ]
        frame_type = 85 /* same_locals_1_stack_item */
          stack = [ class java/lang/Throwable ]
        frame_type = 18 /* same */
}
SourceFile: "Main.java"
